xia_cache_firestore/__init__.py
xia_cache_firestore/cache.cpython-39-x86_64-linux-gnu.so
xia_cache_firestore/connection.cpython-39-x86_64-linux-gnu.so
xia_cache_firestore-0.0.12.dist-info/LICENSE
xia_cache_firestore-0.0.12.dist-info/METADATA
xia_cache_firestore-0.0.12.dist-info/WHEEL
xia_cache_firestore-0.0.12.dist-info/top_level.txt
xia_cache_firestore-0.0.12.dist-info/RECORD
