Metadata-Version: 2.1
Name: xia-cache-firestore
Version: 0.0.12
Summary: Cache Engine with Firestore as backend
Home-page: https://git.top-infra.com/
Author: Xia CHEN
Author-email: admin@x-i-a.com
License: UNKNOWN
Platform: UNKNOWN
Requires-Python: >=3.7
License-File: LICENSE
Requires-Dist: google-cloud-firestore
Requires-Dist: xia-cache
